pandas_utility/__init__.py
pandas_utility/__version__.py
pandas_utility/pandas_utility.py
pandas_utility-0.1.4.dist-info/LICENSE
pandas_utility-0.1.4.dist-info/METADATA
pandas_utility-0.1.4.dist-info/WHEEL
pandas_utility-0.1.4.dist-info/top_level.txt
pandas_utility-0.1.4.dist-info/RECORD
